qemu_runner/__init__.py
qemu_runner/argument.py
qemu_runner/find_qemu.py
qemu_runner/layer.py
qemu_runner/layer_locator.py
qemu_runner/variable_resolution.py
qemu_runner/layers/virt-cortex-m.ini
qemu_runner/make_runner/__init__.py
qemu_runner/make_runner/__main__.py
qemu_runner/make_runner/main.py.in
qemu_runner/make_runner/make.py
qemu_runner/make_runner/runner.py
qemu_runner-1.4.4.dist-info/LICENSE.txt
qemu_runner-1.4.4.dist-info/METADATA
qemu_runner-1.4.4.dist-info/WHEEL
qemu_runner-1.4.4.dist-info/entry_points.txt
qemu_runner-1.4.4.dist-info/top_level.txt
qemu_runner-1.4.4.dist-info/RECORD
