Metadata-Version: 2.1
Name: qemu-runner
Version: 1.4.4
Summary: Create self-contained wrappers around QEMU to hide & share long command-line invocations
Home-page: https://github.com/Novakov/qemu-runner
Author: Maciej Nowak
Classifier: Development Status :: 4 - Beta
Classifier: Environment :: Console
Classifier: Intended Audience :: Developers
Classifier: License :: OSI Approved :: MIT License
Classifier: Operating System :: OS Independent
Classifier: Topic :: Software Development :: Embedded Systems
Classifier: Topic :: System :: Emulators
Classifier: Topic :: Utilities
Requires-Python: >=3.8
License-File: LICENSE.txt
